MANIFEST.in
README.rst
setup.py
ckanext/__init__.py
ckanext/budgets/__init__.py
ckanext/budgets/controllers.py
ckanext/budgets/exceptions.py
ckanext/budgets/plugin.py
ckanext/budgets/data/countries.json
ckanext/budgets/data/currencies.json
ckanext/budgets/data/bdp/schema.json
ckanext/budgets/data/bdp/statuses.json
ckanext/budgets/form/templates/package/snippets/resource_form.html
ckanext/budgets/lib/__init__.py
ckanext/budgets/lib/budgetdatapackage.py
ckanext_budgets.egg-info/PKG-INFO
ckanext_budgets.egg-info/SOURCES.txt
ckanext_budgets.egg-info/dependency_links.txt
ckanext_budgets.egg-info/entry_points.txt
ckanext_budgets.egg-info/namespace_packages.txt
ckanext_budgets.egg-info/not-zip-safe
ckanext_budgets.egg-info/requires.txt
ckanext_budgets.egg-info/top_level.txt