Metadata-Version: 1.1
Name: ckanext-budgets
Version: 0.3.2
Summary: CKAN extension for creating/distributing budget data packages
Home-page: https://github.com/tryggvib/ckanext-budgets
Author: Tryggvi Bjorgvinsson
Author-email: tryggvi.bjorgvinsson@okfn.org
License: AGPLv3
Keywords: ckan
Platform: UNKNOWN
Classifier: Development Status :: 4 - Beta
Classifier: Intended Audience :: Other Audience
Classifier: License :: OSI Approved :: GNU Affero General Public License v3
Classifier: Programming Language :: Python :: 2.7
Classifier: Topic :: Internet :: WWW/HTTP :: Dynamic Content
